setup.py
bin/jc
jenkins_control/__init__.py
jenkins_control/jenkins_control.py
jenkins_control.egg-info/PKG-INFO
jenkins_control.egg-info/SOURCES.txt
jenkins_control.egg-info/dependency_links.txt
jenkins_control.egg-info/requires.txt
jenkins_control.egg-info/top_level.txt