Metadata-Version: 1.1
Name: jenkins-control
Version: 0.2.1
Summary: Simple controls for jenkins
Home-page: https://github.com/marhag87/jenkins_control
Author: marhag87
Author-email: marhag87@gmail.com
License: WTFPL
Platform: UNKNOWN
Classifier: Development Status :: 4 - Beta
Classifier: Intended Audience :: Developers
Classifier: Programming Language :: Python :: 3
